{
  "startedAt": "2026-02-25T08:40:14.213Z",
  "sources": [
    "bing"
  ],
  "maxResults": 20,
  "limitPerSource": 2000,
  "verificationMode": "strict",
  "minScore": 45,
  "requireEmail": true,
  "totalDiscovered": 0,
  "accepted": 0,
  "pendingReview": 0,
  "rejected": 0,
  "appended": 0,
  "stagingFile": "/Users/kiwankim/dir-automation-agencies-01/data/staging/partners_202602250840.csv",
  "qualityGate": {
    "withEmail": 0,
    "validatedWebsite": 0,
    "blockedByDomain": 0,
    "avgVerificationScore": 0
  },
  "candidates": []
}